{"cRsd_2132_auth": "3edfzU1OSsQR9ZdQ0dMUvK0PZpXyE6oOeLGnmNuE6hzwJ%2BIO%2BEAF3%2FUtfaiNBdOL5F%2FpSrFMOE7zh6v%2FF2fHDV2U", "cRsd_2132_checkfollow": "1", "cRsd_2132_lastact": "1681308089%09member.php%09logging", "cRsd_2132_lastcheckfeed": "9518%7C1681308089", "cRsd_2132_lastvisit": "1681304486", "cRsd_2132_lip": "120.236.153.102%2C1681307949", "cRsd_2132_saltkey": "T079qvO8", "cRsd_2132_seccodecSCQNWtr": "139.56534a4e49ad29f585", "cRsd_2132_sid": "CQNWtr", "cRsd_2132_ulastactivity": "1cbcEznHE6UJEUsFL7buKXcq8zeOChDir7%2F6UyeOQ3mNRBfdGti1", "cRsd_2132_vnm7ree_9518": "{\"tid\":\"147197\",\"num\":8}"}